{
    "type": "crafting_shaped",
    "conditions": [
        {
            "type": "forge:mod_loaded",
            "modid": "bigreactors"
        }
    ],
    "pattern": [
        "BAB",
        "CIC",
        "BSB"
    ],
    "key": {
        "I": {
            "tag": "forge:storage_blocks/iron"
        },
        "C": {
            "tag": "forge:workbench"
        },
        "B": {
            "item": "extendedcrafting:basic_component"
        },
        "S": {
            "item": "extendedcrafting:black_iron_slate"
        },
        "A": {
            "item": "extendedcrafting:basic_catalyst"
        }
    },
    "result": {
        "item": "extendedcrafting:basic_table"
    }
}